pylsp_code_actions/__init__.py
pylsp_code_actions/plugin.py
pylsp_code_actions-0.1.dev6.dist-info/licenses/LICENSES/Apache-2.0.txt
pylsp_code_actions-0.1.dev6.dist-info/licenses/LICENSES/CC0-1.0.txt
pylsp_code_actions-0.1.dev6.dist-info/METADATA
pylsp_code_actions-0.1.dev6.dist-info/WHEEL
pylsp_code_actions-0.1.dev6.dist-info/entry_points.txt
pylsp_code_actions-0.1.dev6.dist-info/top_level.txt
pylsp_code_actions-0.1.dev6.dist-info/RECORD
