Metadata-Version: 2.4
Name: pylsp-code-actions
Version: 0.1.dev6
Summary: Handy code actions for python-lsp-server
Author: DB InfraGO AG
License-Expression: Apache-2.0
Project-URL: Homepage, https://github.com/DSD-DBS/pylsp-code-actions
Platform: any
Classifier: Development Status :: 5 - Production/Stable
Classifier: Intended Audience :: Developers
Classifier: Natural Language :: English
Classifier: Operating System :: OS Independent
Classifier: Programming Language :: Python :: 3 :: Only
Classifier: Programming Language :: Python :: 3.10
Classifier: Programming Language :: Python :: 3.11
Classifier: Programming Language :: Python :: 3.12
Classifier: Programming Language :: Python :: 3.13
Classifier: Topic :: Software Development :: Libraries :: Python Modules
Classifier: Typing :: Typed
Requires-Python: >=3.10
License-File: LICENSES/Apache-2.0.txt
License-File: LICENSES/CC0-1.0.txt
Requires-Dist: python-lsp-server<2,>=1.11.0
Dynamic: license-file
